playbook.py
pytest_playbook-0.1.1.dist-info/entry_points.txt
pytest_playbook-0.1.1.dist-info/WHEEL
pytest_playbook-0.1.1.dist-info/METADATA
pytest_playbook-0.1.1.dist-info/RECORD
